openscad_dependencies/__init__.py
openscad_dependencies-0.9.2.dist-info/licenses/LICENSE
openscad_dependencies-0.9.2.dist-info/METADATA
openscad_dependencies-0.9.2.dist-info/WHEEL
openscad_dependencies-0.9.2.dist-info/entry_points.txt
openscad_dependencies-0.9.2.dist-info/top_level.txt
openscad_dependencies-0.9.2.dist-info/RECORD
