Metadata-Version: 2.4
Name: openscad_dependencies
Version: 0.9.2
Summary: A tool for finding dependencies in OpenSCAD language source code.
Author-email: Revar Desmera <revarbat@gmail.com>
Maintainer-email: Revar Desmera <revarbat@gmail.com>
License-Expression: MIT
Project-URL: Homepage, https://github.com/belfryscad/openscad_dependencies
Project-URL: Repository, https://github.com/belfryscad/openscad_dependencies
Project-URL: Bug Tracker, https://github.com/belfryscad/openscad_dependencies/issues
Project-URL: Releases, https://github.com/belfryscad/openscad_dependencies/releases
Project-URL: Usage, https://github.com/belfryscad/openscad_dependencies/README.rst
Keywords: openscad,openscad dependencies,dependencies
Classifier: Development Status :: 3 - Alpha
Classifier: Environment :: Console
Classifier: Intended Audience :: Developers
Classifier: Intended Audience :: Manufacturing
Classifier: Operating System :: MacOS :: MacOS X
Classifier: Operating System :: Microsoft :: Windows
Classifier: Operating System :: POSIX
Classifier: Programming Language :: Python :: 3
Classifier: Topic :: Artistic Software
Classifier: Topic :: Multimedia :: Graphics :: 3D Modeling
Classifier: Topic :: Multimedia :: Graphics :: 3D Rendering
Classifier: Topic :: Software Development :: Libraries
Classifier: Topic :: Software Development :: Libraries :: Python Modules
Requires-Python: >=3.7
License-File: LICENSE
Requires-Dist: arpeggio>=2.0.3
Requires-Dist: openscad_parser>=0.9.2
Dynamic: license-file
